hoonpyutils/BrandMeta.py
hoonpyutils/DatasetMeta.py
hoonpyutils/FaceMeta.py
hoonpyutils/ImageContentMeta.py
hoonpyutils/ImageMeta.py
hoonpyutils/LandmarkMeta.py
hoonpyutils/ObjectMeta.py
hoonpyutils/SceneMeta.py
hoonpyutils/TextMeta.py
hoonpyutils/UtilsCommon.py
hoonpyutils/UtilsGui.py
hoonpyutils/UtilsImage.py
hoonpyutils/UtilsSocket.py
hoonpyutils/UtilsStat.py
hoonpyutils/UtilsVideo.py
hoonpyutils/VideoMeta.py
hoonpyutils/VideoTrackingMeta.py
hoonpyutils/__init__.py
hoonpyutils-0.1.1.dist-info/LICENSE
hoonpyutils-0.1.1.dist-info/METADATA
hoonpyutils-0.1.1.dist-info/WHEEL
hoonpyutils-0.1.1.dist-info/top_level.txt
hoonpyutils-0.1.1.dist-info/RECORD
